five18/__init__.py
five18-0.1.0.dist-info/LICENSE
five18-0.1.0.dist-info/WHEEL
five18-0.1.0.dist-info/METADATA
five18-0.1.0.dist-info/RECORD
