Metadata-Version: 2.1
Name: five18
Version: 0.1.0
Summary: Utilities for dealing with pyproject.toml files
Home-page: https://github.com/mharrisb1/five18
License: MIT
Author: Michael Harris
Author-email: mharris@luabase.com
Requires-Python: >=3.7,<4.0
Classifier: Development Status :: 3 - Alpha
Classifier: Intended Audience :: Developers
Classifier: License :: OSI Approved :: MIT License
Classifier: Programming Language :: Python :: 3
Classifier: Programming Language :: Python :: 3.10
Classifier: Programming Language :: Python :: 3.7
Classifier: Programming Language :: Python :: 3.8
Classifier: Programming Language :: Python :: 3.9
Requires-Dist: tomli (>=2.0.1,<3.0.0); python_version < "3.11"
Project-URL: Documentation, https://github.com/mharrisb1/five18
Project-URL: Repository, https://github.com/mharrisb1/five18
